sslmqs/__init__.py
sslmqs/mqs.py
sslmqs/mqs_async.py
sslmqs/retry.py
sslmqs-2.1.9.dist-info/DESCRIPTION.rst
sslmqs-2.1.9.dist-info/METADATA
sslmqs-2.1.9.dist-info/RECORD
sslmqs-2.1.9.dist-info/WHEEL
sslmqs-2.1.9.dist-info/metadata.json
sslmqs-2.1.9.dist-info/top_level.txt
