Metadata-Version: 2.0
Name: sslmqs
Version: 2.1.9
Summary: An abstraction layer above pika, used to connect to a RabbitMQ cluster with SSL.
Home-page: https://go.pelicandd.com/n/sslmqs
Author: Arseni Mourzenko
Author-email: arseni.mourzenko@pelicandd.com
License: MIT
Keywords: amqp,rabbitmq,ssl,cluster
Platform: UNKNOWN
Requires-Dist: pika (==1.1.0)
Requires-Dist: multiwatch (==1.0.6)
